iob2/__init__.py
iob2/test.py
iob2-1.1.1.dist-info/METADATA
iob2-1.1.1.dist-info/WHEEL
iob2-1.1.1.dist-info/top_level.txt
iob2-1.1.1.dist-info/RECORD
